ga4/__init__.py
ga4/ga4.py
ga4/log/__init__.py
ga4/log/logger.py
ga4-0.1.1.dist-info/WHEEL
ga4-0.1.1.dist-info/METADATA
ga4-0.1.1.dist-info/RECORD
