Metadata-Version: 2.1
Name: ga4
Version: 0.1.1
Summary: 
Author: s4mukka
Author-email: meninosam197@gmail.com
Requires-Python: >=3.8,<4.0
Classifier: Programming Language :: Python :: 3
Classifier: Programming Language :: Python :: 3.10
Classifier: Programming Language :: Python :: 3.8
Classifier: Programming Language :: Python :: 3.9
Requires-Dist: google-analytics-data (>=0.11.2,<0.12.0)
Requires-Dist: pandas (>=1.4.2,<2.0.0)
Requires-Dist: pyspark (>=3.2.1,<4.0.0)
